requests_pprint/__init__.py
requests_pprint/formatting.py
requests_pprint/http_async.py
requests_pprint/http_sync.py
requests_pprint/py.typed
requests_pprint-1.2.4.dist-info/LICENSE
requests_pprint-1.2.4.dist-info/METADATA
requests_pprint-1.2.4.dist-info/WHEEL
requests_pprint-1.2.4.dist-info/RECORD
