Metadata-Version: 2.3
Name: requests-pprint
Version: 1.2.4
Summary: Pretty print your python HTTP requests
License: GPL-3.0-only
Author: YisusChrist
Author-email: agelrenorenardo@gmail.com
Requires-Python: >=3.9
Classifier: License :: OSI Approved :: GNU General Public License v3 (GPLv3)
Classifier: Programming Language :: Python :: 3
Classifier: Programming Language :: Python :: 3.9
Classifier: Programming Language :: Python :: 3.10
Classifier: Programming Language :: Python :: 3.11
Classifier: Programming Language :: Python :: 3.12
Classifier: Programming Language :: Python :: 3.13
Requires-Dist: aiohttp (>=3.9.5,<4.0.0)
Requires-Dist: requests (>=2.31.0,<3.0.0)
Requires-Dist: rich (>=13.7.1)
Project-URL: Repository, https://github.com/yisuschrist/requests-pprint
